alphanum_code/VERSION
alphanum_code/__init__.py
alphanum_code/core.py
tests/__init__.py
tests/test_alphanum_code.py
alphanum_code-0.1.1.dist-info/LICENSE
alphanum_code-0.1.1.dist-info/METADATA
alphanum_code-0.1.1.dist-info/WHEEL
alphanum_code-0.1.1.dist-info/top_level.txt
alphanum_code-0.1.1.dist-info/RECORD
