Metadata-Version: 2.1
Name: alphanum-code
Version: 0.1.1
Summary: AlphaNumeric unique consecutive code generator.
Home-page: https://github.com/ylaizet/alphanum_code
Author: Yec'han Laizet
Author-email: y.laizet@bordeaux.unicancer.fr
License: MIT
Download-URL: https://github.com/ylaizet/alphanum_code/archive/0.1.1.tar.gz
Keywords: code,generator
Platform: UNKNOWN
Classifier: Programming Language :: Python
Classifier: Development Status :: 4 - Beta
Classifier: License :: OSI Approved :: MIT License
Classifier: Natural Language :: English
Classifier: Operating System :: OS Independent
Classifier: Programming Language :: Python :: 2.7
Classifier: Programming Language :: Python :: 3.6
Classifier: Topic :: Scientific/Engineering :: Bio-Informatics
Requires-Dist: SQLAlchemy
